goto_conversion/__init__.py
goto_conversion/probabilityTables/mensProbabilitiesTable2024.csv
goto_conversion/probabilityTables/mensProbabilitiesTable2025.csv
goto_conversion/probabilityTables/womensProbabilitiesTable2024.csv
goto_conversion/probabilityTables/womensProbabilitiesTable2025.csv
goto_conversion-3.0.2.dist-info/licenses/LICENSE.txt
goto_conversion-3.0.2.dist-info/METADATA
goto_conversion-3.0.2.dist-info/WHEEL
goto_conversion-3.0.2.dist-info/top_level.txt
goto_conversion-3.0.2.dist-info/RECORD
