Metadata-Version: 2.4
Name: goto_conversion
Version: 3.0.2
Summary: Powered $47,000 of prize money, over 10 Gold Medals and 100 Medals on Kaggle
Author: Kaito Goto
License-Expression: MIT
Project-URL: Homepage, https://github.com/gotoConversion/goto_conversion
Project-URL: Bug Tracker, https://github.com/gotoConversion/goto_conversion/issues
Keywords: kaggle,betting,bookmaker,sports-analytics,betfair-api
Classifier: Programming Language :: Python :: 3
Classifier: Operating System :: OS Independent
Requires-Python: >=3.7
License-File: LICENSE.txt
Dynamic: license-file
